PyUploadGram/PyUploadGram.py
PyUploadGram/__init__.py
PyUploadGram-1.0.0.dist-info/LICENSE
PyUploadGram-1.0.0.dist-info/METADATA
PyUploadGram-1.0.0.dist-info/WHEEL
PyUploadGram-1.0.0.dist-info/top_level.txt
PyUploadGram-1.0.0.dist-info/RECORD
