Metadata-Version: 2.1
Name: PyUploadGram
Version: 1.0.0
Summary: An API wrapper for UploadGram
Home-page: https://github.com/scrubjay55/PyUploadGram.git
Author: scrubjay55
License: APLv2
Project-URL: Source, https://github.com/scrubjay55/PyUploadGram.git
Platform: UNKNOWN
License-File: LICENSE
Requires-Dist: requests
